[
  {
    "sse": "SSEAmaroni",
    "plant": "AMAR",
    "subsystem": "WPP",
    "section": "L1",
    "device": "AMA01",
    "type": "ALA",
    "name": "[0] WTG System ok",
    "units": ""
  },
  {
    "sse": "SSEAmaroni",
    "plant": "AMAR",
    "subsystem": "WPP",
    "section": "L1",
    "device": "AMA01",
    "type": "ALA",
    "name": "WTG Data Frozen",
    "units": ""
  },
  {
    "sse": "SSEAmaroni",
    "plant": "AMAR",
    "subsystem": "WPP",
    "section": "L1",
    "device": "AMA01",
    "type": "ALA",
    "name": "WTG ErrCom",
    "units": ""
  },
  {
    "sse": "SSEAmaroni",
    "plant": "AMAR",
    "subsystem": "WPP",
    "section": "L1",
    "device": "AMA01",
    "type": "ALA",
    "name": "WTG Fault",
    "units": ""
  },
  {
    "sse": "SSEAmaroni",
    "plant": "AMAR",
    "subsystem": "WPP",
    "section": "L1",
    "device": "AMA01",
    "type": "ALA_THD",
    "name": "Gear BearTemp 1(Gen)",
    "units": ""
  },
  {
    "sse": "SSEAmaroni",
    "plant": "AMAR",
    "subsystem": "WPP",
    "section": "L1",
    "device": "AMA01",
    "type": "ALA_THD",
    "name": "GearBoxOilTemp",
    "units": ""
  },
  {
    "sse": "SSEAmaroni",
    "plant": "AMAR",
    "subsystem": "WPP",
    "section": "L1",
    "device": "AMA01",
    "type": "ALA_THD",
    "name": "Gen BearTemp BS",
    "units": ""
  },
  {
    "sse": "SSEAmaroni",
    "plant": "AMAR",
    "subsystem": "WPP",
    "section": "L1",
    "device": "AMA01",
    "type": "ALA_THD",
    "name": "Gen BearTemp D end",
    "units": ""
  },
  {
    "sse": "SSEAmaroni",
    "plant": "AMAR",
    "subsystem": "WPP",
    "section": "L1",
    "device": "AMA01",
    "type": "ALA_THD",
    "name": "GeneratorL1Temp",
    "units": ""
  },
  {
    "sse": "SSEAmaroni",
    "plant": "AMAR",
    "subsystem": "WPP",
    "section": "L1",
    "device": "AMA01",
    "type": "ALA_THD",
    "name": "GeneratorL2Temp",
    "units": ""
  },
  {
    "sse": "SSEAmaroni",
    "plant": "AMAR",
    "subsystem": "WPP",
    "section": "L1",
    "device": "AMA01",
    "type": "ALA_THD",
    "name": "HydrSystemPress",
    "units": ""
  },
  {
    "sse": "SSEAmaroni",
    "plant": "AMAR",
    "subsystem": "WPP",
    "section": "L1",
    "device": "AMA01",
    "type": "ALA_THD",
    "name": "MainBear Temp 1",
    "units": ""
  },
  {
    "sse": "SSEAmaroni",
    "plant": "AMAR",
    "subsystem": "WPP",
    "section": "L1",
    "device": "AMA01",
    "type": "DMAV",
    "name": "PF",
    "units": ""
  },
  {
    "sse": "SSEAmaroni",
    "plant": "AMAR",
    "subsystem": "WPP",
    "section": "L1",
    "device": "AMA01",
    "type": "DMAV",
    "name": "Power limitation active",
    "units": ""
  },
  {
    "sse": "SSEAmaroni",
    "plant": "AMAR",
    "subsystem": "WPP",
    "section": "L1",
    "device": "AMA01",
    "type": "K",
    "name": "Reset",
    "units": ""
  },
  {
    "sse": "SSEAmaroni",
    "plant": "AMAR",
    "subsystem": "WPP",
    "section": "L1",
    "device": "AMA01",
    "type": "K",
    "name": "Start",
    "units": ""
  },
  {
    "sse": "SSEAmaroni",
    "plant": "AMAR",
    "subsystem": "WPP",
    "section": "L1",
    "device": "AMA01",
    "type": "K",
    "name": "Stop",
    "units": ""
  },
  {
    "sse": "SSEAmaroni",
    "plant": "AMAR",
    "subsystem": "WPP",
    "section": "L1",
    "device": "AMA01",
    "type": "ST",
    "name": "ActiveAlarms",
    "units": ""
  },
  {
    "sse": "SSEAmaroni",
    "plant": "AMAR",
    "subsystem": "WPP",
    "section": "L1",
    "device": "AMA01",
    "type": "ST",
    "name": "Alarm",
    "units": ""
  },
  {
    "sse": "SSEAmaroni",
    "plant": "AMAR",
    "subsystem": "WPP",
    "section": "L1",
    "device": "AMA01",
    "type": "ST",
    "name": "Start_Disable",
    "units": ""
  },
  {
    "sse": "SSEAmaroni",
    "plant": "AMAR",
    "subsystem": "WPP",
    "section": "L1",
    "device": "AMA01",
    "type": "ST",
    "name": "WTG Event",
    "units": ""
  },
  {
    "sse": "SSEAmaroni",
    "plant": "AMAR",
    "subsystem": "WPP",
    "section": "L1",
    "device": "AMA01",
    "type": "ST",
    "name": "WTG Status",
    "units": ""
  },
  {
    "sse": "SSEAmaroni",
    "plant": "AMAR",
    "subsystem": "WPP",
    "section": "L1",
    "device": "AMA01",
    "type": "DMAV",
    "name": "I1",
    "units": "A"
  },
  {
    "sse": "SSEAmaroni",
    "plant": "AMAR",
    "subsystem": "WPP",
    "section": "L1",
    "device": "AMA01",
    "type": "DMAV",
    "name": "I2",
    "units": "A"
  },
  {
    "sse": "SSEAmaroni",
    "plant": "AMAR",
    "subsystem": "WPP",
    "section": "L1",
    "device": "AMA01",
    "type": "DMAV",
    "name": "I3",
    "units": "A"
  },
  {
    "sse": "SSEAmaroni",
    "plant": "AMAR",
    "subsystem": "WPP",
    "section": "L1",
    "device": "AMA01",
    "type": "DMAV",
    "name": "Airpressure",
    "units": "bar"
  },
  {
    "sse": "SSEAmaroni",
    "plant": "AMAR",
    "subsystem": "WPP",
    "section": "L1",
    "device": "AMA01",
    "type": "DMAV",
    "name": "GearboxOilPress",
    "units": "bar"
  },
  {
    "sse": "SSEAmaroni",
    "plant": "AMAR",
    "subsystem": "WPP",
    "section": "L1",
    "device": "AMA01",
    "type": "DMAV",
    "name": "GearBoxOilPressPmp",
    "units": "bar"
  },
  {
    "sse": "SSEAmaroni",
    "plant": "AMAR",
    "subsystem": "WPP",
    "section": "L1",
    "device": "AMA01",
    "type": "DMAV",
    "name": "HydrMainBrakesPressure",
    "units": "bar"
  },
  {
    "sse": "SSEAmaroni",
    "plant": "AMAR",
    "subsystem": "WPP",
    "section": "L1",
    "device": "AMA01",
    "type": "DMAV",
    "name": "HydrSystemPress",
    "units": "bar"
  },
  {
    "sse": "SSEAmaroni",
    "plant": "AMAR",
    "subsystem": "WPP",
    "section": "L1",
    "device": "AMA01",
    "type": "DMAV",
    "name": "Yaw H-AccuPress",
    "units": "bar"
  },
  {
    "sse": "SSEAmaroni",
    "plant": "AMAR",
    "subsystem": "WPP",
    "section": "L1",
    "device": "AMA01",
    "type": "DMAV",
    "name": "YawHydBrkPress",
    "units": "bar"
  },
  {
    "sse": "SSEAmaroni",
    "plant": "AMAR",
    "subsystem": "WPP",
    "section": "L1",
    "device": "AMA01",
    "type": "DMAV",
    "name": "Air Temp CtrlCab",
    "units": "C"
  },
  {
    "sse": "SSEAmaroni",
    "plant": "AMAR",
    "subsystem": "WPP",
    "section": "L1",
    "device": "AMA01",
    "type": "DMAV",
    "name": "Air Temp PwrCab CtrlFld",
    "units": "C"
  },
  {
    "sse": "SSEAmaroni",
    "plant": "AMAR",
    "subsystem": "WPP",
    "section": "L1",
    "device": "AMA01",
    "type": "DMAV",
    "name": "Air Temp PwrCab PwrFld",
    "units": "C"
  },
  {
    "sse": "SSEAmaroni",
    "plant": "AMAR",
    "subsystem": "WPP",
    "section": "L1",
    "device": "AMA01",
    "type": "DMAV",
    "name": "Air Temp TowerBott",
    "units": "C"
  },
  {
    "sse": "SSEAmaroni",
    "plant": "AMAR",
    "subsystem": "WPP",
    "section": "L1",
    "device": "AMA01",
    "type": "DMAV",
    "name": "Ambient Temp",
    "units": "C"
  },
  {
    "sse": "SSEAmaroni",
    "plant": "AMAR",
    "subsystem": "WPP",
    "section": "L1",
    "device": "AMA01",
    "type": "DMAV",
    "name": "Gear BearTemp 1(Gen)",
    "units": "C"
  },
  {
    "sse": "SSEAmaroni",
    "plant": "AMAR",
    "subsystem": "WPP",
    "section": "L1",
    "device": "AMA01",
    "type": "DMAV",
    "name": "Gear BearTemp 2(Rot)",
    "units": "C"
  },
  {
    "sse": "SSEAmaroni",
    "plant": "AMAR",
    "subsystem": "WPP",
    "section": "L1",
    "device": "AMA01",
    "type": "DMAV",
    "name": "GearBoxOilTemp",
    "units": "C"
  },
  {
    "sse": "SSEAmaroni",
    "plant": "AMAR",
    "subsystem": "WPP",
    "section": "L1",
    "device": "AMA01",
    "type": "DMAV",
    "name": "GearBoxOilTemp Sump",
    "units": "C"
  },
  {
    "sse": "SSEAmaroni",
    "plant": "AMAR",
    "subsystem": "WPP",
    "section": "L1",
    "device": "AMA01",
    "type": "DMAV",
    "name": "Gen BearTemp BS",
    "units": "C"
  },
  {
    "sse": "SSEAmaroni",
    "plant": "AMAR",
    "subsystem": "WPP",
    "section": "L1",
    "device": "AMA01",
    "type": "DMAV",
    "name": "Gen BearTemp D end",
    "units": "C"
  },
  {
    "sse": "SSEAmaroni",
    "plant": "AMAR",
    "subsystem": "WPP",
    "section": "L1",
    "device": "AMA01",
    "type": "DMAV",
    "name": "GenCWTempGenInlt",
    "units": "C"
  },
  {
    "sse": "SSEAmaroni",
    "plant": "AMAR",
    "subsystem": "WPP",
    "section": "L1",
    "device": "AMA01",
    "type": "DMAV",
    "name": "GenCWTempGenOutlt",
    "units": "C"
  },
  {
    "sse": "SSEAmaroni",
    "plant": "AMAR",
    "subsystem": "WPP",
    "section": "L1",
    "device": "AMA01",
    "type": "DMAV",
    "name": "GeneratorL1Temp",
    "units": "C"
  },
  {
    "sse": "SSEAmaroni",
    "plant": "AMAR",
    "subsystem": "WPP",
    "section": "L1",
    "device": "AMA01",
    "type": "DMAV",
    "name": "GeneratorL2Temp",
    "units": "C"
  },
  {
    "sse": "SSEAmaroni",
    "plant": "AMAR",
    "subsystem": "WPP",
    "section": "L1",
    "device": "AMA01",
    "type": "DMAV",
    "name": "GeneratorL3Temp",
    "units": "C"
  },
  {
    "sse": "SSEAmaroni",
    "plant": "AMAR",
    "subsystem": "WPP",
    "section": "L1",
    "device": "AMA01",
    "type": "DMAV",
    "name": "HydOilTemp",
    "units": "C"
  },
  {
    "sse": "SSEAmaroni",
    "plant": "AMAR",
    "subsystem": "WPP",
    "section": "L1",
    "device": "AMA01",
    "type": "DMAV",
    "name": "MainBear Temp 1",
    "units": "C"
  },
  {
    "sse": "SSEAmaroni",
    "plant": "AMAR",
    "subsystem": "WPP",
    "section": "L1",
    "device": "AMA01",
    "type": "DMAV",
    "name": "MV TrafoTemp Area-Coil",
    "units": "C"
  },
  {
    "sse": "SSEAmaroni",
    "plant": "AMAR",
    "subsystem": "WPP",
    "section": "L1",
    "device": "AMA01",
    "type": "DMAV",
    "name": "Nacelle Temp",
    "units": "C"
  },
  {
    "sse": "SSEAmaroni",
    "plant": "AMAR",
    "subsystem": "WPP",
    "section": "L1",
    "device": "AMA01",
    "type": "DMAV",
    "name": "Pitch 1 Motor Temp",
    "units": "C"
  },
  {
    "sse": "SSEAmaroni",
    "plant": "AMAR",
    "subsystem": "WPP",
    "section": "L1",
    "device": "AMA01",
    "type": "DMAV",
    "name": "Pitch 2 Motor Temp",
    "units": "C"
  },
  {
    "sse": "SSEAmaroni",
    "plant": "AMAR",
    "subsystem": "WPP",
    "section": "L1",
    "device": "AMA01",
    "type": "DMAV",
    "name": "Pitch 3 Motor Temp",
    "units": "C"
  },
  {
    "sse": "SSEAmaroni",
    "plant": "AMAR",
    "subsystem": "WPP",
    "section": "L1",
    "device": "AMA01",
    "type": "DMAV",
    "name": "Pitch1 Box Temp",
    "units": "C"
  },
  {
    "sse": "SSEAmaroni",
    "plant": "AMAR",
    "subsystem": "WPP",
    "section": "L1",
    "device": "AMA01",
    "type": "DMAV",
    "name": "Pitch2 Box Temp",
    "units": "C"
  },
  {
    "sse": "SSEAmaroni",
    "plant": "AMAR",
    "subsystem": "WPP",
    "section": "L1",
    "device": "AMA01",
    "type": "DMAV",
    "name": "Pitch3 Box Temp",
    "units": "C"
  },
  {
    "sse": "SSEAmaroni",
    "plant": "AMAR",
    "subsystem": "WPP",
    "section": "L1",
    "device": "AMA01",
    "type": "DMAV",
    "name": "Vib Y-direction",
    "units": "cm/s2"
  },
  {
    "sse": "SSEAmaroni",
    "plant": "AMAR",
    "subsystem": "WPP",
    "section": "L1",
    "device": "AMA01",
    "type": "DMAV",
    "name": "Vib Z-direction",
    "units": "cm/s2"
  },
  {
    "sse": "SSEAmaroni",
    "plant": "AMAR",
    "subsystem": "WPP",
    "section": "L1",
    "device": "AMA01",
    "type": "DMAV",
    "name": "Blade Pitch Angle",
    "units": "grad"
  },
  {
    "sse": "SSEAmaroni",
    "plant": "AMAR",
    "subsystem": "WPP",
    "section": "L1",
    "device": "AMA01",
    "type": "DMAV",
    "name": "Blade Pitch angle 1",
    "units": "grad"
  },
  {
    "sse": "SSEAmaroni",
    "plant": "AMAR",
    "subsystem": "WPP",
    "section": "L1",
    "device": "AMA01",
    "type": "DMAV",
    "name": "Blade Pitch angle 2",
    "units": "grad"
  },
  {
    "sse": "SSEAmaroni",
    "plant": "AMAR",
    "subsystem": "WPP",
    "section": "L1",
    "device": "AMA01",
    "type": "DMAV",
    "name": "Blade Pitch angle 3",
    "units": "grad"
  },
  {
    "sse": "SSEAmaroni",
    "plant": "AMAR",
    "subsystem": "WPP",
    "section": "L1",
    "device": "AMA01",
    "type": "DMAV",
    "name": "Nacelle Dir",
    "units": "grad"
  },
  {
    "sse": "SSEAmaroni",
    "plant": "AMAR",
    "subsystem": "WPP",
    "section": "L1",
    "device": "AMA01",
    "type": "DMAV",
    "name": "Wind Dir",
    "units": "grad"
  },
  {
    "sse": "SSEAmaroni",
    "plant": "AMAR",
    "subsystem": "WPP",
    "section": "L1",
    "device": "AMA01",
    "type": "DMAV",
    "name": "Yaw CableTwist",
    "units": "grad"
  },
  {
    "sse": "SSEAmaroni",
    "plant": "AMAR",
    "subsystem": "WPP",
    "section": "L1",
    "device": "AMA01",
    "type": "DMSD",
    "name": "Wind Dir",
    "units": "grad"
  },
  {
    "sse": "SSEAmaroni",
    "plant": "AMAR",
    "subsystem": "WPP",
    "section": "L1",
    "device": "AMA01",
    "type": "DMAV",
    "name": "F",
    "units": "Hz"
  },
  {
    "sse": "SSEAmaroni",
    "plant": "AMAR",
    "subsystem": "WPP",
    "section": "L1",
    "device": "AMA01",
    "type": "DMAV",
    "name": "V12",
    "units": "kV"
  },
  {
    "sse": "SSEAmaroni",
    "plant": "AMAR",
    "subsystem": "WPP",
    "section": "L1",
    "device": "AMA01",
    "type": "DMAV",
    "name": "V23",
    "units": "kV"
  },
  {
    "sse": "SSEAmaroni",
    "plant": "AMAR",
    "subsystem": "WPP",
    "section": "L1",
    "device": "AMA01",
    "type": "DMAV",
    "name": "V31",
    "units": "kV"
  },
  {
    "sse": "SSEAmaroni",
    "plant": "AMAR",
    "subsystem": "WPP",
    "section": "L1",
    "device": "AMA01",
    "type": "DMAV",
    "name": "Apparent Power",
    "units": "KVA"
  },
  {
    "sse": "SSEAmaroni",
    "plant": "AMAR",
    "subsystem": "WPP",
    "section": "L1",
    "device": "AMA01",
    "type": "DMAV",
    "name": "Reactive Power",
    "units": "kVar"
  },
  {
    "sse": "SSEAmaroni",
    "plant": "AMAR",
    "subsystem": "WPP",
    "section": "L1",
    "device": "AMA01",
    "type": "DE",
    "name": "Reactive Energy Cap",
    "units": "kVarh"
  },
  {
    "sse": "SSEAmaroni",
    "plant": "AMAR",
    "subsystem": "WPP",
    "section": "L1",
    "device": "AMA01",
    "type": "DE",
    "name": "Reactive Energy Ind",
    "units": "kVarh"
  },
  {
    "sse": "SSEAmaroni",
    "plant": "AMAR",
    "subsystem": "WPP",
    "section": "L1",
    "device": "AMA01",
    "type": "DMAV",
    "name": "Active Power",
    "units": "kW"
  },
  {
    "sse": "SSEAmaroni",
    "plant": "AMAR",
    "subsystem": "WPP",
    "section": "L1",
    "device": "AMA01",
    "type": "DMAV",
    "name": "Active Power Limit",
    "units": "kW"
  },
  {
    "sse": "SSEAmaroni",
    "plant": "AMAR",
    "subsystem": "WPP",
    "section": "L1",
    "device": "AMA01",
    "type": "DMAV",
    "name": "Producible Power (Vendor)",
    "units": "kW"
  },
  {
    "sse": "SSEAmaroni",
    "plant": "AMAR",
    "subsystem": "WPP",
    "section": "L1",
    "device": "AMA01",
    "type": "TMAV",
    "name": "Active Power",
    "units": "kW"
  },
  {
    "sse": "SSEAmaroni",
    "plant": "AMAR",
    "subsystem": "WPP",
    "section": "L1",
    "device": "AMA01",
    "type": "DE",
    "name": "Active Energy Exp",
    "units": "kWh"
  },
  {
    "sse": "SSEAmaroni",
    "plant": "AMAR",
    "subsystem": "WPP",
    "section": "L1",
    "device": "AMA01",
    "type": "DE",
    "name": "Active Energy Imp",
    "units": "kWh"
  },
  {
    "sse": "SSEAmaroni",
    "plant": "AMAR",
    "subsystem": "WPP",
    "section": "L1",
    "device": "AMA01",
    "type": "DMAV",
    "name": "Wind Speed",
    "units": "m/s"
  },
  {
    "sse": "SSEAmaroni",
    "plant": "AMAR",
    "subsystem": "WPP",
    "section": "L1",
    "device": "AMA01",
    "type": "DMMAX",
    "name": "Wind Speed",
    "units": "m/s"
  },
  {
    "sse": "SSEAmaroni",
    "plant": "AMAR",
    "subsystem": "WPP",
    "section": "L1",
    "device": "AMA01",
    "type": "DMMIN",
    "name": "Wind Speed",
    "units": "m/s"
  },
  {
    "sse": "SSEAmaroni",
    "plant": "AMAR",
    "subsystem": "WPP",
    "section": "L1",
    "device": "AMA01",
    "type": "DMSD",
    "name": "Wind Speed",
    "units": "m/s"
  },
  {
    "sse": "SSEAmaroni",
    "plant": "AMAR",
    "subsystem": "WPP",
    "section": "L1",
    "device": "AMA01",
    "type": "DMAV",
    "name": "Generator RPM",
    "units": "RPM"
  },
  {
    "sse": "SSEAmaroni",
    "plant": "AMAR",
    "subsystem": "WPP",
    "section": "L1",
    "device": "AMA01",
    "type": "DMAV",
    "name": "Rotor RPM",
    "units": "RPM"
  },
  {
    "sse": "SSEAmaroni",
    "plant": "AMAR",
    "subsystem": "WPP",
    "section": "L1",
    "device": "AMA01",
    "type": "DMAV",
    "name": "WTG Status",
    "units": ""
  },
  {
    "sse": "SSEAmaroni",
    "plant": "AMAR",
    "subsystem": "WPP",
    "section": "L1",
    "device": "AMA01",
    "type": "QAV",
    "name": "WTG Status",
    "units": ""
  },
  {
    "sse": "SSEAmaroni",
    "plant": "AMAR",
    "subsystem": "WPP",
    "section": "L1",
    "device": "AMA01",
    "type": "DMAV",
    "name": "WTG Event",
    "units": ""
  },
  {
    "sse": "SSEAmaroni",
    "plant": "AMAR",
    "subsystem": "WPP",
    "section": "L1",
    "device": "AMA01",
    "type": "QAV",
    "name": "WTG Event",
    "units": ""
  }
]